<?xml version='1.0' encoding='utf-8'?><m:page id='04773ae4-40e1-4c53-81a8-9243a252ca96' xmlns='http://www.w3.org/1999/xhtml' title='अपनी प्रतिक्रिया साझा करें' cancelChangesOperationId='M1PUoMDckUiT4bs/kH/Q9A' xmlns:m='http://schemas.mendix.com/forms/1.0'><m:parameters>[]</m:parameters><m:layouts><m:layout path='Atlas_Core/PopupLayout.layout.xml'></m:layout></m:layouts><m:arguments><m:argument parameterName='9d772ec0-1a7b-4831-a243-f55cad0b014e'><div data-mendix-id='20.FeedbackModule.ShareFeedback_Hindi.layoutGrid1' data-mendix-type='mxui.widget.ReactWidgetWrapper' data-mendix-props='"widgetTree":[{"$widgetId":"20.FeedbackModule.ShareFeedback_Hindi.layoutGrid1","widget":"Div","props":{"class":"mx-name-layoutGrid1 mx-layoutgrid mx-layoutgrid-fluid container-fluid","content":[{"$widgetId":"20.FeedbackModule.ShareFeedback_Hindi.layoutGrid1$row0","widget":"Div","props":{"class":"row","content":[{"$widgetId":"20.FeedbackModule.ShareFeedback_Hindi.layoutGrid1$row0$column0","widget":"Div","props":{"class":"col-lg col-md col","content":[{"$widgetId":"20.FeedbackModule.ShareFeedback_Hindi.dataView5","widget":"DataView","props":{"class":"mx-name-dataView5 form-vertical","object":{"$type":"NanoflowObjectProperty","dataSourceId":"20.21","editable":true,"source":{"nanoflow":"FeedbackModule.DS_FeedbackForm"},"argMap":{}},"emptyMessage":{"$type":"TextProperty","value":""},"body":[{"$widgetId":"20.FeedbackModule.ShareFeedback_Hindi.container5","widget":"Container","props":{"class":"mx-name-container5 spacing-outer-bottom-medium","renderMode":"div","onClick":null,"content":[{"$widgetId":"20.FeedbackModule.ShareFeedback_Hindi.text1","widget":"Text","props":{"class":"mx-name-text1","caption":{"$type":"ExpressionProperty","expression":{"expr":{"type":"literal","value":"अपने अनुभव को बेहतर बनाने में हमारी सहायता करें और अपनी प्रतिक्रिया हमारे साथ शेयर करें!"},"args":{}}},"renderMode":"p"}},{"$widgetId":"20.FeedbackModule.ShareFeedback_Hindi.feedback_subject$formGroup","widget":"FormGroup","props":{"class":"mx-name-feedback_subject mx-textbox","control":[{"$widgetId":"20.FeedbackModule.ShareFeedback_Hindi.feedback_subject","widget":"TextBox","props":{"inputValue":{"$type":"AttributeProperty","scope":"20.FeedbackModule.ShareFeedback_Hindi.dataView5","path":"","entity":"FeedbackModule.Feedback","attribute":"Subject","onChange":{"type":"callNanoflow","argMap":{"Feedback":{"widget":"20.FeedbackModule.ShareFeedback_Hindi.dataView5","source":"object"}},"config":{"nanoflow":"FeedbackModule.OCH_SaveToLocalStorage"},"disabledDuringExecution":false},"isList":false,"validation":null,"formatting":{}},"isPassword":false,"placeholder":{"$type":"ExpressionProperty","expression":{"expr":{"type":"literal","value":"अपनी प्रतिक्रिया को कुछ शब्दों में संक्षेपित करें"},"args":{}}},"mask":"","readOnlyStyle":"control","maxLength":200,"onEnter":null,"onLeave":null,"onEnterKeyPress":null,"autocomplete":"on","submitWhileEditing":true,"submitDelay":300,"id":{"$type":"DerivedUniqueIdProperty","widgetId":"20.FeedbackModule.ShareFeedback_Hindi.feedback_subject"}}}],"caption":{"$type":"ExpressionProperty","expression":{"expr":{"type":"literal","value":"विषय"},"args":{}}},"labelFor":{"$type":"DerivedUniqueIdProperty","widgetId":"20.FeedbackModule.ShareFeedback_Hindi.feedback_subject"},"orientation":"vertical","hasError":{"$type":"ValidationProperty","inputWidgetId":"20.FeedbackModule.ShareFeedback_Hindi.feedback_subject"}}},{"$widgetId":"20.FeedbackModule.ShareFeedback_Hindi.textArea2$formGroup","widget":"FormGroup","props":{"class":"mx-name-textArea2 mx-textarea","control":[{"$widgetId":"20.FeedbackModule.ShareFeedback_Hindi.textArea2","widget":"TextArea","props":{"inputValue":{"$type":"AttributeProperty","scope":"20.FeedbackModule.ShareFeedback_Hindi.dataView5","path":"","entity":"FeedbackModule.Feedback","attribute":"Description","onChange":{"type":"callNanoflow","argMap":{"Feedback":{"widget":"20.FeedbackModule.ShareFeedback_Hindi.dataView5","source":"object"}},"config":{"nanoflow":"FeedbackModule.OCH_SaveToLocalStorage"},"disabledDuringExecution":false},"isList":false,"validation":null},"numberOfLines":5,"autoGrow":false,"placeholder":{"$type":"ExpressionProperty","expression":{"expr":{"type":"literal","value":"कृपया एक विस्तृत विवरण जोड़ें, जिसमें समस्या ढूंढने से पहले आपके द्वारा उठाए गए कदम शामिल हों, या यह विचार आपके और अन्य उपयोगकर्ताओं के अनुभव को बेहतर बनाने में कैसे मदद करेगा"},"args":{}}},"readOnlyStyle":"control","onEnter":null,"onLeave":null,"submitWhileEditing":true,"submitDelay":300,"id":{"$type":"DerivedUniqueIdProperty","widgetId":"20.FeedbackModule.ShareFeedback_Hindi.textArea2"}}}],"caption":{"$type":"ExpressionProperty","expression":{"expr":{"type":"literal","value":"विवरण"},"args":{}}},"labelFor":{"$type":"DerivedUniqueIdProperty","widgetId":"20.FeedbackModule.ShareFeedback_Hindi.textArea2"},"orientation":"vertical","hasError":{"$type":"ValidationProperty","inputWidgetId":"20.FeedbackModule.ShareFeedback_Hindi.textArea2"}}}],"ariaHidden":false}},{"$widgetId":"20.FeedbackModule.ShareFeedback_Hindi.container4","widget":"Container","props":{"class":"mx-name-container4 col-left spacing-outer-bottom","renderMode":"div","onClick":null,"content":[{"$widgetId":"20.FeedbackModule.ShareFeedback_Hindi.label1","widget":"Label","props":{"class":"mx-name-label1 text-semibold spacing-outer-bottom-none","id":{"$type":"DerivedUniqueIdProperty","widgetId":"20.FeedbackModule.ShareFeedback_Hindi.label1"},"caption":{"$type":"TextProperty","value":"फ़ाइलों को संलग्न करें"}}},{"$widgetId":"20.FeedbackModule.ShareFeedback_Hindi.text2","widget":"Text","props":{"class":"mx-name-text2 text-light","caption":{"$type":"ExpressionProperty","expression":{"expr":{"type":"literal","value":"अधिकतम एक jpg, jpeg, png या gif छवि फ़ाइल अपलोड करें। 5MB."},"args":{}}},"renderMode":"span"}}],"ariaHidden":false}},{"$widgetId":"20.FeedbackModule.ShareFeedback_Hindi.container2","widget":"Container","props":{"class":"mx-name-container2 flexcontainer justify-content-start spacing-outer-bottom-medium","style":{"gap":"8px"},"renderMode":"div","onClick":null,"content":[{"$widgetId":"20.FeedbackModule.ShareFeedback_Hindi.actionButton4","widget":"ActionButton","props":{"buttonId":"20.FeedbackModule.ShareFeedback_Hindi.actionButton4","class":"mx-name-actionButton4","renderType":"button","buttonClass":"btn-default","caption":{"$type":"ExpressionProperty","expression":{"expr":{"type":"literal","value":"स्क्रीनशॉट लीजिये"},"args":{}}},"tooltip":{"$type":"TextProperty","value":""},"icon":{"$type":"WebIconProperty","icon":{"type":"glyph","iconClass":"glyphicon-camera"}},"action":{"$type":"ActionProperty","action":{"type":"callNanoflow","argMap":{"Feedback":{"widget":"20.FeedbackModule.ShareFeedback_Hindi.dataView5","source":"object"}},"config":{"nanoflow":"FeedbackModule.ACT_TriggerScreenshotMode"},"disabledDuringExecution":true},"abortOnServerValidation":true}}},{"$widgetId":"20.FeedbackModule.ShareFeedback_Hindi.actionButton5","widget":"ActionButton","props":{"buttonId":"20.FeedbackModule.ShareFeedback_Hindi.actionButton5","class":"mx-name-actionButton5","renderType":"button","buttonClass":"btn-default","caption":{"$type":"ExpressionProperty","expression":{"expr":{"type":"literal","value":"अपलोड"},"args":{}}},"tooltip":{"$type":"TextProperty","value":""},"icon":{"$type":"WebIconProperty","icon":{"type":"glyph","iconClass":"glyphicon-open"}},"action":{"$type":"ActionProperty","action":{"type":"callNanoflow","argMap":{"Feedback":{"widget":"20.FeedbackModule.ShareFeedback_Hindi.dataView5","source":"object"}},"config":{"nanoflow":"FeedbackModule.ACT_UploadImage"},"disabledDuringExecution":true},"abortOnServerValidation":true}}}],"ariaHidden":false}},{"$widgetId":"20.FeedbackModule.ShareFeedback_Hindi.container6$visibility","widget":"ConditionalVisibilityWrapper","props":{"visible":{"$type":"ExpressionProperty","expression":{"expr":{"type":"function","name":"!=","parameters":[{"type":"variable","variable":"currentObject","path":"ImageB64"},{"type":"literal","value":null}]},"args":{"currentObject":{"widget":"20.FeedbackModule.ShareFeedback_Hindi.dataView5","source":"object"}}}},"contents":[{"$widgetId":"20.FeedbackModule.ShareFeedback_Hindi.container6","widget":"Container","props":{"class":"mx-name-container6 mxfeedback-screenshot-preview spacing-outer-bottom-medium","renderMode":"div","onClick":null,"content":[{"$widgetId":"20.FeedbackModule.ShareFeedback_Hindi.container7","widget":"Container","props":{"class":"mx-name-container7","style":{"position":"relative"},"renderMode":"div","onClick":null,"content":[{"$widgetId":"20.FeedbackModule.ShareFeedback_Hindi.actionButton1","widget":"ActionButton","props":{"buttonId":"20.FeedbackModule.ShareFeedback_Hindi.actionButton1","class":"mx-name-actionButton1 mxfeedback-screenshot-preview__delete-button","renderType":"button","buttonClass":"btn-default","caption":{"$type":"ExpressionProperty","expression":{"expr":{"type":"literal","value":""},"args":{}}},"tooltip":{"$type":"TextProperty","value":""},"icon":{"$type":"WebIconProperty","icon":{"type":"glyph","iconClass":"glyphicon-remove"}},"action":{"$type":"ActionProperty","action":{"type":"callNanoflow","argMap":{"Feedback":{"widget":"20.FeedbackModule.ShareFeedback_Hindi.dataView5","source":"object"}},"config":{"nanoflow":"FeedbackModule.ACT_ClearImage"},"disabledDuringExecution":true},"abortOnServerValidation":true}}},{"$widgetId":"20.FeedbackModule.ShareFeedback_Hindi.image1","widget":"com.mendix.widget.web.image.Image","props":{"datasource":"imageUrl","imageUrl":{"$type":"ExpressionProperty","expression":{"expr":{"type":"variable","variable":"currentObject","path":"ImageB64"},"args":{"currentObject":{"widget":"20.FeedbackModule.ShareFeedback_Hindi.dataView5","source":"object"}}}},"isBackgroundImage":false,"children":null,"onClickType":"action","onClick":null,"alternativeText":{"$type":"ExpressionProperty","expression":{"expr":{"type":"literal","value":"A Preview of the Feedback image that was from the screenshot or upload"},"args":{}}},"widthUnit":"auto","width":100,"heightUnit":"auto","height":100,"iconSize":14,"displayAs":"fullImage","responsive":true,"class":"mx-name-image1 mxfeedback-screenshot-preview__image img-center img-contain","style":{"width":"auto"}}}],"ariaHidden":false}}],"ariaHidden":false}}]}},{"$widgetId":"20.FeedbackModule.ShareFeedback_Hindi.textBox1$formGroup$visibility","widget":"ConditionalVisibilityWrapper","props":{"visible":{"$type":"ExpressionProperty","expression":{"expr":{"type":"variable","variable":"currentObject","path":"_showEmail"},"args":{"currentObject":{"widget":"20.FeedbackModule.ShareFeedback_Hindi.dataView5","source":"object"}}}},"contents":[{"$widgetId":"20.FeedbackModule.ShareFeedback_Hindi.textBox1$formGroup","widget":"FormGroup","props":{"class":"mx-name-textBox1 mx-textbox","control":[{"$widgetId":"20.FeedbackModule.ShareFeedback_Hindi.textBox1","widget":"TextBox","props":{"inputValue":{"$type":"AttributeProperty","scope":"20.FeedbackModule.ShareFeedback_Hindi.dataView5","path":"","entity":"FeedbackModule.Feedback","attribute":"SubmitterEmail","onChange":{"type":"callNanoflow","argMap":{"Feedback":{"widget":"20.FeedbackModule.ShareFeedback_Hindi.dataView5","source":"object"}},"config":{"nanoflow":"FeedbackModule.OCH_SaveToLocalStorage"},"disabledDuringExecution":false},"isList":false,"validation":null,"formatting":{}},"isPassword":false,"placeholder":{"$type":"ExpressionProperty","expression":{"expr":{"type":"literal","value":"name@company.com"},"args":{}}},"mask":"","readOnlyStyle":"control","maxLength":200,"onEnter":null,"onLeave":null,"onEnterKeyPress":null,"autocomplete":"on","submitWhileEditing":true,"submitDelay":300,"id":{"$type":"DerivedUniqueIdProperty","widgetId":"20.FeedbackModule.ShareFeedback_Hindi.textBox1"}}}],"caption":{"$type":"ExpressionProperty","expression":{"expr":{"type":"literal","value":"ईमेल"},"args":{}}},"labelFor":{"$type":"DerivedUniqueIdProperty","widgetId":"20.FeedbackModule.ShareFeedback_Hindi.textBox1"},"orientation":"vertical","hasError":{"$type":"ValidationProperty","inputWidgetId":"20.FeedbackModule.ShareFeedback_Hindi.textBox1"}}}]}},{"$widgetId":"20.FeedbackModule.ShareFeedback_Hindi.container3","widget":"Container","props":{"class":"mx-name-container3 flex-row flexcontainer justify-content-end","style":{"gap":"8px"},"renderMode":"div","onClick":null,"content":[{"$widgetId":"20.FeedbackModule.ShareFeedback_Hindi.feedback_cancel","widget":"ActionButton","props":{"buttonId":"20.FeedbackModule.ShareFeedback_Hindi.feedback_cancel","class":"mx-name-feedback_cancel mxfeedback-feedback-form__cancel-button","renderType":"link","role":"button","buttonClass":"btn-default","caption":{"$type":"ExpressionProperty","expression":{"expr":{"type":"literal","value":"प्रतिक्रिया साफ़ करें"},"args":{}}},"tooltip":{"$type":"TextProperty","value":""},"action":{"$type":"ActionProperty","action":{"type":"closePage","argMap":{},"config":{},"disabledDuringExecution":true},"abortOnServerValidation":true}}},{"$widgetId":"20.FeedbackModule.ShareFeedback_Hindi.feedback_clear","widget":"ActionButton","props":{"buttonId":"20.FeedbackModule.ShareFeedback_Hindi.feedback_clear","class":"mx-name-feedback_clear btn-bordered","renderType":"button","buttonClass":"btn-default","caption":{"$type":"ExpressionProperty","expression":{"expr":{"type":"literal","value":"प्रतिक्रिया रद्द करें"},"args":{}}},"tooltip":{"$type":"TextProperty","value":""},"action":{"$type":"ActionProperty","action":{"type":"callNanoflow","argMap":{"Feedback":{"widget":"20.FeedbackModule.ShareFeedback_Hindi.dataView5","source":"object"}},"config":{"nanoflow":"FeedbackModule.ACT_ClearForm"},"disabledDuringExecution":true},"abortOnServerValidation":true}}},{"$widgetId":"20.FeedbackModule.ShareFeedback_Hindi.feedback_submit","widget":"ActionButton","props":{"buttonId":"20.FeedbackModule.ShareFeedback_Hindi.feedback_submit","class":"mx-name-feedback_submit","renderType":"button","buttonClass":"btn-primary","caption":{"$type":"ExpressionProperty","expression":{"expr":{"type":"literal","value":"सबमिट करें"},"args":{}}},"tooltip":{"$type":"TextProperty","value":""},"action":{"$type":"ActionProperty","action":{"type":"callNanoflow","argMap":{"Feedback":{"widget":"20.FeedbackModule.ShareFeedback_Hindi.dataView5","source":"object"}},"config":{"nanoflow":"FeedbackModule.ACT_SubmitFeedback"},"disabledDuringExecution":true},"abortOnServerValidation":true}}}],"ariaHidden":false}}],"hideFooter":true,"footer":null}}]}}]}}]}}],"selections":[]'></div></m:argument></m:arguments><m:nanoflows>{"FeedbackModule.DS_FeedbackForm":{"name":"FeedbackModule.DS_FeedbackForm","instructions":[{"type":"nanoflowCall","label":"11bf381d-5625-406d-8256-964ed7da4b24","flow":"FeedbackModule.SUB_GetOrCreateFeedback","parameters":[],"outputVar":"Feedback"},{"type":"microflowCall","label":"81bd5277-0b8e-4c31-bd79-092c5ba8730a","operationId":"Io7eaZoJclqF05B9iiUiOw","parameters":[{"name":"Feedback","value":{"type":"variable","variable":"Feedback"},"kind":"object"}]},{"type":"changeObject","label":"76268226-db36-470d-8370-a2765f20550b","inputVar":"Feedback","member":"_showEmail","value":{"type":"conditional","condition":{"type":"conditional","condition":{"type":"function","name":"!=","parameters":[{"type":"variable","variable":"Feedback","path":"SubmitterEmail"},{"type":"literal","value":null}]},"then":{"type":"function","name":"!=","parameters":[{"type":"variable","variable":"Feedback","path":"SubmitterEmail"},{"type":"literal","value":""}]},"else":{"type":"literal","value":false}},"then":{"type":"literal","value":false},"else":{"type":"literal","value":true}}},{"type":"javaScriptActionCall","label":"ea3f7190-e417-422a-ab59-3bd94acded95","action":"FeedbackModule.JS_PopulateFeedbackMetadata","parameters":[{"kind":"object","value":{"type":"variable","variable":"Feedback"}}]},{"type":"javaScriptActionCall","label":"acadabe8-fdd5-4128-b0be-d8e52d60d453","action":"FeedbackModule.SetStorageItemObject","parameters":[{"kind":"primitive","value":{"type":"constant","name":"FeedbackModule.LocalStorageKey"}},{"kind":"object","value":{"type":"variable","variable":"Feedback"}}]},{"type":"return","label":"106eef7f-ba7a-4502-9b43-0c8c9c182110","result":{"type":"variable","variable":"Feedback"},"resultKind":"object"}]},"FeedbackModule.OCH_SaveToLocalStorage":{"name":"FeedbackModule.OCH_SaveToLocalStorage","instructions":[{"type":"javaScriptActionCall","label":"fcd124ed-819b-43f5-b3ef-ade01a49a449","action":"FeedbackModule.SetStorageItemObject","parameters":[{"kind":"primitive","value":{"type":"constant","name":"FeedbackModule.LocalStorageKey"}},{"kind":"object","value":{"type":"variable","variable":"Feedback"}}]},{"type":"return","label":"d06bdf25-4d0b-4e66-8402-5b4fe05f4df9","result":{"type":"literal","value":null},"resultKind":"primitive"}]},"FeedbackModule.ACT_TriggerScreenshotMode":{"name":"FeedbackModule.ACT_TriggerScreenshotMode","instructions":[{"type":"closeForm","label":"fbc2447f-d521-45fe-8c2b-db5c3a8efa51"},{"type":"javaScriptActionCall","label":"c868cbab-b38b-4c00-a621-b7fed0388923","action":"FeedbackModule.JS_ToggleFeedbackScreenshotWidget","outputVar":"base64FromWidget","parameters":[]},{"type":"switch","label":"cb404c75-754f-4e90-9159-060b44a38774","condition":{"type":"function","name":"!=","parameters":[{"type":"variable","variable":"base64FromWidget"},{"type":"literal","value":"uploadCancelled"}]},"targets":{"true":"dc1f341e-7e38-46e4-ab94-88894689f379","false":"3e7be5c6-4917-40e5-8b19-15cb0182d241"}},{"type":"jump","label":"3e7be5c6-4917-40e5-8b19-15cb0182d241","target":"4e0ac521-6dfe-42a9-9b3d-9dba909428a1"},{"type":"jump","label":"4e0ac521-6dfe-42a9-9b3d-9dba909428a1","target":"7ab23f7a-dd59-472f-a2d1-4dbe0a84f66d"},{"type":"jump","label":"7ab23f7a-dd59-472f-a2d1-4dbe0a84f66d","target":"2b8f96fd-22a2-4f0d-8c00-bb4fda985f55"},{"type":"openForm","label":"2b8f96fd-22a2-4f0d-8c00-bb4fda985f55","path":"FeedbackModule/ShareFeedback.page.xml","params":{"name":"FeedbackModule/ShareFeedback.page.xml","location":"modal","resizable":true}},{"type":"return","label":"a85fca8b-2420-47b5-a953-6bfe10385be7","result":{"type":"literal","value":null},"resultKind":"primitive"},{"type":"switch","label":"dc1f341e-7e38-46e4-ab94-88894689f379","condition":{"type":"function","name":"!=","parameters":[{"type":"variable","variable":"base64FromWidget"},{"type":"literal","value":null}]},"targets":{"true":"1e7b7555-b00d-4c33-9021-eadaefad499e","false":"9b0b230b-88e9-42fb-9ad0-4c4a869a0657"}},{"type":"return","label":"9b0b230b-88e9-42fb-9ad0-4c4a869a0657","result":{"type":"literal","value":null},"resultKind":"primitive"},{"type":"changeObject","label":"1e7b7555-b00d-4c33-9021-eadaefad499e","inputVar":"Feedback","member":"ImageB64","value":{"type":"variable","variable":"base64FromWidget"}},{"type":"commitObjects","operationId":"iHyDGLjky0aAdtNc73ihWQ","inputVar":"Feedback"},{"type":"jump","label":"7ab23f7a-dd59-472f-a2d1-4dbe0a84f66d","target":"2b8f96fd-22a2-4f0d-8c00-bb4fda985f55"}]},"FeedbackModule.ACT_UploadImage":{"name":"FeedbackModule.ACT_UploadImage","instructions":[{"type":"setVariable","label":"95d8d14d-a475-4838-b8c4-87f6018777cf","value":{"type":"literal","value":".gif,.png,.jpg,.jpeg"},"outputVar":"mimeTypes","outputKind":"primitive"},{"type":"setVariable","label":"adfe34de-2f06-445d-b096-ae32b2fc2e60","value":{"type":"literalNumeric","value":"5"},"outputVar":"fileUploadSize","outputKind":"primitive"},{"type":"javaScriptActionCall","label":"a4ed8012-44fb-44e1-923f-062b347d2ac6","action":"FeedbackModule.JS_UploadAndConvertToFileBlobURL","outputVar":"fileBlobURL","parameters":[{"kind":"primitive","value":{"type":"variable","variable":"mimeTypes"}},{"kind":"primitive","value":{"type":"variable","variable":"fileUploadSize"}}]},{"type":"switch","label":"d089840c-0a07-4f68-b89f-2541bd9e3639","condition":{"type":"function","name":"!=","parameters":[{"type":"variable","variable":"fileBlobURL"},{"type":"literal","value":"uploadCancelled"}]},"targets":{"true":"d74c50dc-4f58-4c4b-8aa0-7005cf22f339","false":"7eec1100-4da4-434a-ba80-16c6163de25a"}},{"type":"return","label":"7eec1100-4da4-434a-ba80-16c6163de25a","result":{"type":"literal","value":null},"resultKind":"primitive"},{"type":"switch","label":"d74c50dc-4f58-4c4b-8aa0-7005cf22f339","condition":{"type":"function","name":"!=","parameters":[{"type":"variable","variable":"fileBlobURL"},{"type":"literal","value":null}]},"targets":{"false":"f6123341-642b-442f-a4ad-39a945e961c1","true":"1b3d55c1-7837-4595-9c1e-0de3e416f085"}},{"type":"switch","label":"1b3d55c1-7837-4595-9c1e-0de3e416f085","condition":{"type":"function","name":"!=","parameters":[{"type":"variable","variable":"fileBlobURL"},{"type":"literal","value":"fileSizeNotAccepted"}]},"targets":{"true":"a379707a-add4-4f95-bd57-119c2e6e0a16","false":"a1d83870-1fa7-497e-91e5-246d4c26d66c"}},{"type":"showMessage","label":"a1d83870-1fa7-497e-91e5-246d4c26d66c","messageType":"error","message":{"type":"literal","value":"Maximum image size allowed is 5MB."},"blocking":true},{"type":"return","label":"9e229d04-65a3-4b60-b260-59476f610784","result":{"type":"literal","value":null},"resultKind":"primitive"},{"type":"switch","label":"a379707a-add4-4f95-bd57-119c2e6e0a16","condition":{"type":"function","name":"!=","parameters":[{"type":"variable","variable":"fileBlobURL"},{"type":"literal","value":"fileTypeNotAccepted"}]},"targets":{"false":"7416782b-1bd9-4001-87ac-e8d780880059","true":"9c15d6b8-e92f-4cab-9de9-12bfdab03f42"}},{"type":"closeForm","label":"9c15d6b8-e92f-4cab-9de9-12bfdab03f42"},{"type":"javaScriptActionCall","label":"6de3c6f6-6cf9-41c9-a7be-e5f2c189b432","action":"FeedbackModule.JS_ToggleFeedbackAnnotateWidget","outputVar":"base64ImageFromWidget","parameters":[{"kind":"primitive","value":{"type":"variable","variable":"fileBlobURL"}}]},{"type":"changeObject","label":"79f60aea-5fad-43cf-bc05-0dcc0dd25526","inputVar":"Feedback","member":"ImageB64","value":{"type":"variable","variable":"base64ImageFromWidget"}},{"type":"commitObjects","operationId":"T3iKFS895E2EgfvaU1LhKw","inputVar":"Feedback"},{"type":"openForm","label":"ebc32a70-358f-424f-82e9-69c653f20ddf","path":"FeedbackModule/ShareFeedback.page.xml","params":{"name":"FeedbackModule/ShareFeedback.page.xml","location":"modal","resizable":true}},{"type":"javaScriptActionCall","label":"4e7b2962-0d51-4e07-ad5a-2f1718b3b0ef","action":"FeedbackModule.SetStorageItemObject","parameters":[{"kind":"primitive","value":{"type":"constant","name":"FeedbackModule.LocalStorageKey"}},{"kind":"object","value":{"type":"variable","variable":"Feedback"}}]},{"type":"javaScriptActionCall","label":"baf9db12-76ac-4f7a-8fe7-392e63596ee5","action":"FeedbackModule.JS_RevokeUploadedFileFromMemory","parameters":[{"kind":"primitive","value":{"type":"variable","variable":"fileBlobURL"}}]},{"type":"return","label":"20050cc2-a21c-46f9-b036-bc1023bfadc6","result":{"type":"literal","value":null},"resultKind":"primitive"},{"type":"showMessage","label":"7416782b-1bd9-4001-87ac-e8d780880059","messageType":"error","message":{"type":"literal","value":"Only images with format of .gif .jpg .jpeg .png are allowed"},"blocking":true},{"type":"return","label":"93c592bd-c9b6-484d-b0bf-6803232eca5c","result":{"type":"literal","value":null},"resultKind":"primitive"},{"type":"showMessage","label":"f6123341-642b-442f-a4ad-39a945e961c1","messageType":"error","message":{"type":"literal","value":"Upload failed, please try again."},"blocking":true},{"type":"return","label":"8578f068-8c3d-4b82-a9a1-640296b89ac7","result":{"type":"literal","value":null},"resultKind":"primitive"}]},"FeedbackModule.ACT_ClearImage":{"name":"FeedbackModule.ACT_ClearImage","instructions":[{"type":"changeObject","label":"2ebedd87-5419-4e48-adb4-338b18460564","inputVar":"Feedback","member":"ImageB64","value":{"type":"literal","value":null}},{"type":"javaScriptActionCall","label":"69065b47-ab46-41e8-afe4-e5a15c972c26","action":"FeedbackModule.SetStorageItemObject","parameters":[{"kind":"primitive","value":{"type":"constant","name":"FeedbackModule.LocalStorageKey"}},{"kind":"object","value":{"type":"variable","variable":"Feedback"}}]},{"type":"return","label":"2f8604dc-47b2-4909-90e7-1d2c63978fcf","result":{"type":"literal","value":null},"resultKind":"primitive"}]},"FeedbackModule.ACT_ClearForm":{"name":"FeedbackModule.ACT_ClearForm","instructions":[{"type":"changeObject","label":"376096d1-0eec-4a50-af5d-06636781dccb","inputVar":"Feedback","member":"Subject","value":{"type":"literal","value":null}},{"type":"changeObject","inputVar":"Feedback","member":"Description","value":{"type":"literal","value":null}},{"type":"changeObject","inputVar":"Feedback","member":"SubmitterEmail","value":{"type":"literal","value":null}},{"type":"changeObject","inputVar":"Feedback","member":"ImageB64","value":{"type":"literal","value":null}},{"type":"javaScriptActionCall","label":"2830e6aa-60a3-4011-86c5-fe434c008bc3","action":"FeedbackModule.SetStorageItemObject","parameters":[{"kind":"primitive","value":{"type":"constant","name":"FeedbackModule.LocalStorageKey"}},{"kind":"object","value":{"type":"variable","variable":"Feedback"}}]},{"type":"return","label":"56e8d062-75da-46c4-a4e3-3f7cf8e542b0","result":{"type":"literal","value":null},"resultKind":"primitive"}]},"FeedbackModule.ACT_SubmitFeedback":{"name":"FeedbackModule.ACT_SubmitFeedback","instructions":[{"type":"setVariable","label":"c2454dd5-012f-471c-b3d8-2455f5f5c351","value":{"type":"literal","value":"English"},"outputVar":"Language","outputKind":"primitive"},{"type":"microflowCall","label":"4c26a3f6-3687-44f7-9a64-3db53566a908","operationId":"Xq8qqgdGvFS5fzTjza+eLg","parameters":[{"name":"Feedback","value":{"type":"variable","variable":"Feedback"},"kind":"object"}],"outputVar":"isValid"},{"type":"switch","label":"f4d95978-dad0-47e9-a816-54b566b70081","condition":{"type":"variable","variable":"isValid"},"targets":{"true":"0b3474c6-7835-404e-b2ac-91b5e3cdd67f","false":"1e7faa16-c731-49ca-b586-44116fb0acdd"}},{"type":"return","label":"1e7faa16-c731-49ca-b586-44116fb0acdd","result":{"type":"literal","value":null},"resultKind":"primitive"},{"type":"microflowCall","label":"0b3474c6-7835-404e-b2ac-91b5e3cdd67f","operationId":"u4z+7z0Ujl+luJ3Otqpu+w","parameters":[{"name":"Feedback","value":{"type":"variable","variable":"Feedback"},"kind":"object"}],"outputVar":"ResponseHelper"},{"type":"nanoflowCall","label":"0eaf7950-ca1e-4975-a375-29e419bf64cc","flow":"FeedbackModule.SUB_OpenModalPopUp","parameters":[{"name":"Langauge","value":{"type":"variable","variable":"Language"},"kind":"primitive"},{"name":"ResponseHelper","value":{"type":"variable","variable":"ResponseHelper"},"kind":"object"}]},{"type":"nanoflowCall","label":"ea6c3148-2190-4d48-a99b-b4778b3af4d6","flow":"FeedbackModule.SUB_ResetLocalStorage","parameters":[{"name":"Feedback","value":{"type":"variable","variable":"Feedback"},"kind":"object"}]},{"type":"return","label":"9a74a3c0-439b-4123-be2b-414d85faceb6","result":{"type":"literal","value":null},"resultKind":"primitive"}]},"FeedbackModule.SUB_GetOrCreateFeedback":{"name":"FeedbackModule.SUB_GetOrCreateFeedback","instructions":[{"type":"tryCatch","label":"a0b9d1ef-2561-440a-b60b-1104c5f8c0ac","catchTarget":"d05d5113-d937-4df8-92d5-df34124133f7","body":[{"type":"javaScriptActionCall","action":"FeedbackModule.GetStorageItemObject","outputVar":"LocalFeedback","parameters":[{"kind":"primitive","value":{"type":"constant","name":"FeedbackModule.LocalStorageKey"}},{"kind":"primitive","value":{"type":"literal","value":"FeedbackModule.Feedback"}}]},{"type":"return","result":{"type":"literal","value":true},"resultKind":"primitive"}]},{"type":"switch","label":"39058c95-59e2-4e51-a46f-b9c7a3bdb070","condition":{"type":"function","name":"!=","parameters":[{"type":"variable","variable":"LocalFeedback"},{"type":"literal","value":null}]},"targets":{"false":"ed7e9fd2-4aa8-4363-9c13-d200313d5d06","true":"8626c3ec-4e53-4b2a-a729-2bf58f736a4b"}},{"type":"return","label":"8626c3ec-4e53-4b2a-a729-2bf58f736a4b","result":{"type":"variable","variable":"LocalFeedback"},"resultKind":"object"},{"type":"jump","label":"ed7e9fd2-4aa8-4363-9c13-d200313d5d06","target":"dc8343df-c319-409e-8375-329612eafc98"},{"type":"createObject","label":"dc8343df-c319-409e-8375-329612eafc98","objectType":"FeedbackModule.Feedback","outputVar":"NewFeedback"},{"type":"return","label":"e6c48fe1-459c-421b-bcbe-0266cf5aed7c","result":{"type":"variable","variable":"NewFeedback"},"resultKind":"object"},{"type":"jump","label":"d05d5113-d937-4df8-92d5-df34124133f7","target":"ed7e9fd2-4aa8-4363-9c13-d200313d5d06"},{"type":"jump","label":"ed7e9fd2-4aa8-4363-9c13-d200313d5d06","target":"dc8343df-c319-409e-8375-329612eafc98"}]},"FeedbackModule.SUB_OpenModalPopUp":{"name":"FeedbackModule.SUB_OpenModalPopUp","instructions":[{"type":"switch","label":"b240e08b-86cb-49dd-899f-281a725f13d8","condition":{"type":"function","name":"=","parameters":[{"type":"variable","variable":"Langauge"},{"type":"literal","value":"English"}]},"targets":{"true":"85185ce8-fe74-475b-9a41-267b7747fdc3","false":"a98918f9-a4ba-4ea0-82a4-9bd90c9ebd1a"}},{"type":"switch","label":"a98918f9-a4ba-4ea0-82a4-9bd90c9ebd1a","condition":{"type":"function","name":"=","parameters":[{"type":"variable","variable":"Langauge"},{"type":"literal","value":"Dutch"}]},"targets":{"true":"2e3a4b12-d875-48a4-a55e-97fc20a0975d","false":"a45a31bd-e24f-442e-aaea-9e6c5a44a77c"}},{"type":"switch","label":"a45a31bd-e24f-442e-aaea-9e6c5a44a77c","condition":{"type":"function","name":"=","parameters":[{"type":"variable","variable":"Langauge"},{"type":"literal","value":"French"}]},"targets":{"false":"040bd320-78e6-400b-9dba-97a0a67a50fe","true":"ab75d2b2-da5f-4c3f-8218-b1566b0f0e57"}},{"type":"switch","label":"ab75d2b2-da5f-4c3f-8218-b1566b0f0e57","condition":{"type":"function","name":"!=","parameters":[{"type":"variable","variable":"ResponseHelper"},{"type":"literal","value":null}]},"targets":{"true":"a04098f9-8b53-4d6b-a354-a47f32cedaaa","false":"dcef0b04-68c7-47cb-890e-4b0b8c43f57b"}},{"type":"jump","label":"dcef0b04-68c7-47cb-890e-4b0b8c43f57b","target":"4723fa3e-7d38-41de-ac6f-45f0e7993c65"},{"type":"openForm","label":"4723fa3e-7d38-41de-ac6f-45f0e7993c65","path":"FeedbackModule/PopupFailure_French.page.xml","params":{"name":"FeedbackModule/PopupFailure_French.page.xml","location":"modal","resizable":false},"numberOfPagesToClose":{"type":"literalNumeric","value":"1"}},{"type":"return","label":"016e6708-4921-48e3-8ee4-781a82a83467","result":{"type":"literal","value":null},"resultKind":"primitive"},{"type":"openForm","label":"a04098f9-8b53-4d6b-a354-a47f32cedaaa","path":"FeedbackModule/PopupSuccess_French.page.xml","params":{"name":"FeedbackModule/PopupSuccess_French.page.xml","location":"modal","resizable":false},"inputArgs":{"$Response":{"type":"variable","variable":"ResponseHelper"}},"numberOfPagesToClose":{"type":"literalNumeric","value":"1"}},{"type":"return","label":"5ba13af2-aaab-4ec8-bcfb-43e9ff06776c","result":{"type":"literal","value":null},"resultKind":"primitive"},{"type":"switch","label":"040bd320-78e6-400b-9dba-97a0a67a50fe","condition":{"type":"function","name":"=","parameters":[{"type":"variable","variable":"Langauge"},{"type":"literal","value":"German"}]},"targets":{"false":"ae11eda8-381c-4eac-845d-f914ba130d6a","true":"45a6e202-9186-402d-a740-884cbdbef192"}},{"type":"switch","label":"45a6e202-9186-402d-a740-884cbdbef192","condition":{"type":"function","name":"!=","parameters":[{"type":"variable","variable":"ResponseHelper"},{"type":"literal","value":null}]},"targets":{"true":"295d4049-0501-4b56-bdc2-d08f24aaaf22","false":"3aa86ae8-8445-4fa7-83c8-3bb70812e9e9"}},{"type":"jump","label":"3aa86ae8-8445-4fa7-83c8-3bb70812e9e9","target":"b975a773-c5d6-4d81-a0c0-95286660bacd"},{"type":"openForm","label":"b975a773-c5d6-4d81-a0c0-95286660bacd","path":"FeedbackModule/PopupFailure_German.page.xml","params":{"name":"FeedbackModule/PopupFailure_German.page.xml","location":"modal","resizable":false},"numberOfPagesToClose":{"type":"literalNumeric","value":"1"}},{"type":"return","label":"55c43640-cd66-4a53-acf3-57ab46cb0b99","result":{"type":"literal","value":null},"resultKind":"primitive"},{"type":"openForm","label":"295d4049-0501-4b56-bdc2-d08f24aaaf22","path":"FeedbackModule/PopupSuccess_German.page.xml","params":{"name":"FeedbackModule/PopupSuccess_German.page.xml","location":"modal","resizable":false},"inputArgs":{"$Response":{"type":"variable","variable":"ResponseHelper"}},"numberOfPagesToClose":{"type":"literalNumeric","value":"1"}},{"type":"return","label":"9d1d06ca-33c9-433f-a818-1431267958e9","result":{"type":"literal","value":null},"resultKind":"primitive"},{"type":"switch","label":"ae11eda8-381c-4eac-845d-f914ba130d6a","condition":{"type":"function","name":"=","parameters":[{"type":"variable","variable":"Langauge"},{"type":"literal","value":"Hindi"}]},"targets":{"false":"23bb27ea-25e7-4de9-b0dc-0145dce8e090","true":"5ff4f8eb-78aa-4f62-96cf-3993dec5ebfb"}},{"type":"switch","label":"5ff4f8eb-78aa-4f62-96cf-3993dec5ebfb","condition":{"type":"function","name":"!=","parameters":[{"type":"variable","variable":"ResponseHelper"},{"type":"literal","value":null}]},"targets":{"true":"5844718e-d930-4559-9391-a3c48d40b1d3","false":"5a6e0a4b-bfd0-4954-b0fa-71dcc052fbcb"}},{"type":"jump","label":"5a6e0a4b-bfd0-4954-b0fa-71dcc052fbcb","target":"6d3b5cf5-be72-4d1e-a479-dcc33bc120cd"},{"type":"openForm","label":"6d3b5cf5-be72-4d1e-a479-dcc33bc120cd","path":"FeedbackModule/PopupFailure_Hindi.page.xml","params":{"name":"FeedbackModule/PopupFailure_Hindi.page.xml","location":"modal","resizable":false},"numberOfPagesToClose":{"type":"literalNumeric","value":"1"}},{"type":"return","label":"18255a78-00c8-4aee-99bd-09ba63e25c2d","result":{"type":"literal","value":null},"resultKind":"primitive"},{"type":"openForm","label":"5844718e-d930-4559-9391-a3c48d40b1d3","path":"FeedbackModule/PopupSuccess_Hindi.page.xml","params":{"name":"FeedbackModule/PopupSuccess_Hindi.page.xml","location":"modal","resizable":false},"inputArgs":{"$Response":{"type":"variable","variable":"ResponseHelper"}},"numberOfPagesToClose":{"type":"literalNumeric","value":"1"}},{"type":"return","label":"237851fa-39a4-4e95-9c60-111813ad4e8a","result":{"type":"literal","value":null},"resultKind":"primitive"},{"type":"switch","label":"23bb27ea-25e7-4de9-b0dc-0145dce8e090","condition":{"type":"function","name":"=","parameters":[{"type":"variable","variable":"Langauge"},{"type":"literal","value":"Portuguese"}]},"targets":{"true":"4934617c-baba-40e2-aaa6-76dd6b05d589","false":"398cc5e7-1eb1-4d3d-8aef-7ebb3403d227"}},{"type":"switch","label":"398cc5e7-1eb1-4d3d-8aef-7ebb3403d227","condition":{"type":"function","name":"=","parameters":[{"type":"variable","variable":"Langauge"},{"type":"literal","value":"Spanish"}]},"targets":{"true":"85a7de2f-2e1a-4c66-a5ce-9039727e0f19","false":"5b1a0049-5a37-441c-856a-5b46feb60360"}},{"type":"switch","label":"5b1a0049-5a37-441c-856a-5b46feb60360","condition":{"type":"function","name":"=","parameters":[{"type":"variable","variable":"Langauge"},{"type":"literal","value":"Turkish"}]},"targets":{"true":"ecc09585-5611-4ed6-af20-5542164f1bd2","false":"67ee2e3e-191f-4b57-a930-0ea415252a2d"}},{"type":"showMessage","label":"67ee2e3e-191f-4b57-a930-0ea415252a2d","messageType":"error","message":{"type":"literal","value":"Please configure the language in ACT_SubmitFeedback nanoflow."},"blocking":true},{"type":"return","label":"e5f45b2a-6146-498a-b005-da6d86f716e5","result":{"type":"literal","value":null},"resultKind":"primitive"},{"type":"switch","label":"ecc09585-5611-4ed6-af20-5542164f1bd2","condition":{"type":"function","name":"!=","parameters":[{"type":"variable","variable":"ResponseHelper"},{"type":"literal","value":null}]},"targets":{"true":"3f93e036-29ae-477e-b26d-c8a659835dde","false":"b8ef9306-16b6-4d1b-8370-490e823c09e2"}},{"type":"jump","label":"b8ef9306-16b6-4d1b-8370-490e823c09e2","target":"6a307da0-3494-4702-8bd6-9c8050e99178"},{"type":"openForm","label":"6a307da0-3494-4702-8bd6-9c8050e99178","path":"FeedbackModule/PopupFailure_Turkish.page.xml","params":{"name":"FeedbackModule/PopupFailure_Turkish.page.xml","location":"modal","resizable":false},"numberOfPagesToClose":{"type":"literalNumeric","value":"1"}},{"type":"return","label":"a5055ff0-fe9c-4f4a-b616-aaac5c7d943d","result":{"type":"literal","value":null},"resultKind":"primitive"},{"type":"openForm","label":"3f93e036-29ae-477e-b26d-c8a659835dde","path":"FeedbackModule/PopupSuccess_Turkish.page.xml","params":{"name":"FeedbackModule/PopupSuccess_Turkish.page.xml","location":"modal","resizable":false},"inputArgs":{"$Response":{"type":"variable","variable":"ResponseHelper"}},"numberOfPagesToClose":{"type":"literalNumeric","value":"1"}},{"type":"return","label":"15cf0663-7a26-4044-aa10-fa4f470a79db","result":{"type":"literal","value":null},"resultKind":"primitive"},{"type":"switch","label":"85a7de2f-2e1a-4c66-a5ce-9039727e0f19","condition":{"type":"function","name":"!=","parameters":[{"type":"variable","variable":"ResponseHelper"},{"type":"literal","value":null}]},"targets":{"true":"be46739b-09ee-4a18-bc76-267d154e3f51","false":"0fecc78d-ee15-4182-a81f-9339fa4e9f15"}},{"type":"jump","label":"0fecc78d-ee15-4182-a81f-9339fa4e9f15","target":"a2b8efcf-607e-4d3b-a514-b8e2ea458797"},{"type":"openForm","label":"a2b8efcf-607e-4d3b-a514-b8e2ea458797","path":"FeedbackModule/PopupFailure_Spanish.page.xml","params":{"name":"FeedbackModule/PopupFailure_Spanish.page.xml","location":"modal","resizable":false},"numberOfPagesToClose":{"type":"literalNumeric","value":"1"}},{"type":"return","label":"6ec3ad9c-adf3-448f-85f9-3dbf886f4701","result":{"type":"literal","value":null},"resultKind":"primitive"},{"type":"openForm","label":"be46739b-09ee-4a18-bc76-267d154e3f51","path":"FeedbackModule/PopupSuccess_Spanish.page.xml","params":{"name":"FeedbackModule/PopupSuccess_Spanish.page.xml","location":"modal","resizable":false},"inputArgs":{"$Response":{"type":"variable","variable":"ResponseHelper"}},"numberOfPagesToClose":{"type":"literalNumeric","value":"1"}},{"type":"return","label":"d8509686-7d59-46db-b599-cddd0ed92ce4","result":{"type":"literal","value":null},"resultKind":"primitive"},{"type":"switch","label":"4934617c-baba-40e2-aaa6-76dd6b05d589","condition":{"type":"function","name":"!=","parameters":[{"type":"variable","variable":"ResponseHelper"},{"type":"literal","value":null}]},"targets":{"true":"afe404c2-b846-4359-a121-0483bd2ffd7a","false":"a7d5696c-2e57-4319-8e5c-9d52ea3f1918"}},{"type":"jump","label":"a7d5696c-2e57-4319-8e5c-9d52ea3f1918","target":"e46a5be6-9b87-419e-a808-4c15c4022099"},{"type":"openForm","label":"e46a5be6-9b87-419e-a808-4c15c4022099","path":"FeedbackModule/PopupFailure_Portuguese.page.xml","params":{"name":"FeedbackModule/PopupFailure_Portuguese.page.xml","location":"modal","resizable":false},"numberOfPagesToClose":{"type":"literalNumeric","value":"1"}},{"type":"return","label":"6c811e7b-74d5-487c-9cc6-2333db023d95","result":{"type":"literal","value":null},"resultKind":"primitive"},{"type":"openForm","label":"afe404c2-b846-4359-a121-0483bd2ffd7a","path":"FeedbackModule/PopupSuccess_Portuguese.page.xml","params":{"name":"FeedbackModule/PopupSuccess_Portuguese.page.xml","location":"modal","resizable":false},"inputArgs":{"$Response":{"type":"variable","variable":"ResponseHelper"}},"numberOfPagesToClose":{"type":"literalNumeric","value":"1"}},{"type":"return","label":"e896cf16-0c23-4e09-9172-b9e8f575998b","result":{"type":"literal","value":null},"resultKind":"primitive"},{"type":"switch","label":"2e3a4b12-d875-48a4-a55e-97fc20a0975d","condition":{"type":"function","name":"!=","parameters":[{"type":"variable","variable":"ResponseHelper"},{"type":"literal","value":null}]},"targets":{"true":"7bccfeff-8c09-4d29-b73b-01f24837373a","false":"ab90755a-6c26-4304-95a2-61b11f7a6682"}},{"type":"jump","label":"ab90755a-6c26-4304-95a2-61b11f7a6682","target":"1f586d0e-cba7-4f1c-b5fa-1982dbc12a6e"},{"type":"openForm","label":"1f586d0e-cba7-4f1c-b5fa-1982dbc12a6e","path":"FeedbackModule/PopupFailure_Dutch.page.xml","params":{"name":"FeedbackModule/PopupFailure_Dutch.page.xml","location":"modal","resizable":false},"numberOfPagesToClose":{"type":"literalNumeric","value":"1"}},{"type":"return","label":"8be6f6bb-9107-40c1-b87d-0a91c9f0bc93","result":{"type":"literal","value":null},"resultKind":"primitive"},{"type":"openForm","label":"7bccfeff-8c09-4d29-b73b-01f24837373a","path":"FeedbackModule/PopupSuccess_Dutch.page.xml","params":{"name":"FeedbackModule/PopupSuccess_Dutch.page.xml","location":"modal","resizable":false},"inputArgs":{"$Response":{"type":"variable","variable":"ResponseHelper"}},"numberOfPagesToClose":{"type":"literalNumeric","value":"1"}},{"type":"return","label":"0fdee66c-d6b9-49f5-95a2-e568f1987d53","result":{"type":"literal","value":null},"resultKind":"primitive"},{"type":"switch","label":"85185ce8-fe74-475b-9a41-267b7747fdc3","condition":{"type":"function","name":"!=","parameters":[{"type":"variable","variable":"ResponseHelper"},{"type":"literal","value":null}]},"targets":{"true":"1c2f24d7-294e-48d3-8444-d2685e7e6895","false":"2dac6b47-01a8-426c-baf3-088f0de23c94"}},{"type":"jump","label":"2dac6b47-01a8-426c-baf3-088f0de23c94","target":"176e3600-edf4-461a-a4f2-bcc561a26e1e"},{"type":"openForm","label":"176e3600-edf4-461a-a4f2-bcc561a26e1e","path":"FeedbackModule/PopupFailure_English.page.xml","params":{"name":"FeedbackModule/PopupFailure_English.page.xml","location":"modal","resizable":false},"numberOfPagesToClose":{"type":"literalNumeric","value":"1"}},{"type":"return","label":"5efb4a9b-279a-4a2a-bde8-4da5c8a84827","result":{"type":"literal","value":null},"resultKind":"primitive"},{"type":"openForm","label":"1c2f24d7-294e-48d3-8444-d2685e7e6895","path":"FeedbackModule/PopupSuccess_English.page.xml","params":{"name":"FeedbackModule/PopupSuccess_English.page.xml","location":"modal","resizable":false},"inputArgs":{"$Response":{"type":"variable","variable":"ResponseHelper"}},"numberOfPagesToClose":{"type":"literalNumeric","value":"1"}},{"type":"return","label":"b8fb2064-0d2e-409a-a4d6-969810fefa6d","result":{"type":"literal","value":null},"resultKind":"primitive"}]},"FeedbackModule.SUB_ResetLocalStorage":{"name":"FeedbackModule.SUB_ResetLocalStorage","instructions":[{"type":"changeObject","label":"824e71cb-8ab8-4cdf-b832-3f20fd016766","inputVar":"Feedback","member":"Subject","value":{"type":"literal","value":null}},{"type":"changeObject","inputVar":"Feedback","member":"Description","value":{"type":"literal","value":null}},{"type":"changeObject","inputVar":"Feedback","member":"SubmitterEmail","value":{"type":"literal","value":null}},{"type":"changeObject","inputVar":"Feedback","member":"SubmitterUUID","value":{"type":"literal","value":null}},{"type":"changeObject","inputVar":"Feedback","member":"SubmitterDisplayName","value":{"type":"literal","value":null}},{"type":"changeObject","inputVar":"Feedback","member":"ImageB64","value":{"type":"literal","value":null}},{"type":"changeObject","inputVar":"Feedback","member":"ActiveUserRoles","value":{"type":"literal","value":null}},{"type":"changeObject","inputVar":"Feedback","member":"PageName","value":{"type":"literal","value":null}},{"type":"changeObject","inputVar":"Feedback","member":"Browser","value":{"type":"literal","value":null}},{"type":"changeObject","inputVar":"Feedback","member":"EnvironmentURL","value":{"type":"literal","value":null}},{"type":"changeObject","inputVar":"Feedback","member":"ScreenshotName","value":{"type":"literal","value":null}},{"type":"changeObject","inputVar":"Feedback","member":"Priority","value":{"type":"literal","value":null}},{"type":"changeObject","inputVar":"Feedback","member":"ScreenWidth","value":{"type":"literal","value":null}},{"type":"changeObject","inputVar":"Feedback","member":"ScreenHeight","value":{"type":"literal","value":null}},{"type":"javaScriptActionCall","label":"50ff127c-f3fa-432f-a3e3-3d9cc38f6c22","action":"FeedbackModule.SetStorageItemObject","parameters":[{"kind":"primitive","value":{"type":"constant","name":"FeedbackModule.LocalStorageKey"}},{"kind":"object","value":{"type":"variable","variable":"Feedback"}}]},{"type":"return","label":"667a2e7a-6be8-4753-90d5-a5a8e72cab8e","result":{"type":"literal","value":null},"resultKind":"primitive"}]}}</m:nanoflows><m:enums>{"FeedbackModule.TranslationLanguages":[["Dutch","Dutch"],["English","English"],["French","French"],["German","German"],["Hindi","Hindi"],["Portuguese","Portuguese"],["Spanish","Spanish"],["Turkish","Turkish"]]}</m:enums></m:page>